beproud/__init__.py
beproud/django/__init__.py
beproud/django/mailer/__init__.py
beproud/django/mailer/api.py
beproud/django/mailer/models.py
beproud/django/mailer/signals.py
beproud/django/mailer/tasks.py
beproud/django/mailer/backends/__init__.py
beproud/django/mailer/backends/base.py
beproud/django/mailer/backends/console.py
beproud/django/mailer/backends/dummy.py
beproud/django/mailer/backends/filebased.py
beproud/django/mailer/backends/locmem.py
beproud/django/mailer/backends/smtp.py
beproud/django/mailer/templates/mailer/html_mail.tpl
beproud/django/mailer/templates/mailer/mail.tpl
beproud/django/mailer/templatetags/__init__.py
beproud/django/mailer/templatetags/mailer_tags.py
docs/ja/source/conf.py
tests/__init__.py
tests/settings.py
tests/test_mail.py
bpmailer-1.3.dist-info/METADATA
bpmailer-1.3.dist-info/WHEEL
bpmailer-1.3.dist-info/top_level.txt
bpmailer-1.3.dist-info/RECORD
